cbloss/__init__.py
cbloss/loss.py
cbloss-0.2.0.dist-info/LICENSE
cbloss-0.2.0.dist-info/METADATA
cbloss-0.2.0.dist-info/WHEEL
cbloss-0.2.0.dist-info/top_level.txt
cbloss-0.2.0.dist-info/RECORD
